{
    "title": "Theoretische Physik 4A (Statistische Mechanik und Thermodynamik) (TUM, Modul PH0008)",
    "titleEn": "Theoretical Physics 4A (Statistical Mechanics and Thermodynamics) (TUM, Module PH0008)",
    "description": "Statistische Mechanik und Thermodynamik: statistische Begründung der Thermodynamik (Ensembles, Entropie, Hauptsätze), phänomenologische Thermodynamik (Potentiale, Phasen, Zustandsänderungen), Quantengase und Wechselwirkungen (Fermi/Bose, BE-Kondensation, Strahlung, Ising, Virialentwicklung), Nichtgleichgewichts-Thermodynamik (Boltzmann-Gleichung, Diffusion, Fluktuations-Dissipation). Gesamtaufwand 270 h (davon 120 h Präsenz), 9 ECTS, angeboten im Wintersemester. Version 2025w verantwortet von Rabl, Peter.",
    "descriptionEn": "Statistical mechanics and thermodynamics: statistical justification of thermodynamics (ensembles, entropy, laws), phenomenological thermodynamics (potentials, phases, changes of state), quantum gases and interactions (Fermi/Bose, BE condensation, radiation, Ising, virial expansion), non-equilibrium thermodynamics (Boltzmann equation, diffusion, fluctuation-dissipation). Total workload 270 h (of which 120 h attendance), 9 ECTS, offered in the winter semester. Version 2025w responsible: Rabl, Peter.",
    "landscapeId": "0e5fc3ca-41d7-478f-a8b2-fe33506b7506",
    "locale": "de-DE",
    "subject": "Physik",
    "frameworkId": "tum-ph0008",
    "filters": [
        {
            "id": "BSc",
            "label": "Bachelor Physik"
        }
    ],
    "goals": [
        {
            "id": "2675baa5-3d1a-40ac-973a-44309add152b",
            "shortKey": "tum_ph0008_module",
            "title": "Theoretische Physik 4A – Statistische Mechanik und Thermodynamik (Gesamtmodul)",
            "titleEn": "Theoretical Physics 4A – Statistical Mechanics and Thermodynamics (Full Module)",
            "description": "Studierende verstehen statistische Grundlagen der Thermodynamik, können klassische und Quantengase beschreiben, Phasenübergänge/Wechselwirkungen einordnen und Grundideen der Nichtgleichgewichts-Thermodynamik anwenden.",
            "descriptionEn": "Students understand statistical foundations of thermodynamics, can describe classical and quantum gases, classify phase transitions/interactions, and apply basic ideas of non-equilibrium thermodynamics.",
            "core": true,
            "weight": 5,
            "phase": "Modul",
            "area": "Gesamtkompetenz",
            "tags": [
                "ects:9",
                "workload:270h",
                "presence:120h",
                "level:bachelor",
                "duration:1_semester",
                "language:de",
                "module:PH0008",
                "semester:WS",
                "responsible:rabl_peter"
            ],
            "contains": [
                "0ad131b5-1205-4e6b-9795-270510338340",
                "7d7a839e-064d-40cf-8c9d-7a668be9f0e8",
                "3ced904f-a2b5-4e56-b5d7-526a81b46460",
                "256e621c-c8ec-4a6b-ab01-cd3fcc34605e"
            ],
            "requires": [
                "74d926f1-9733-4868-8e94-b4193e89f2e4",
                "db25b3ae-628d-4bad-ab21-11873874e666",
                "c3ec94a7-8d54-4cc7-8498-7470e2d4d867"
            ],
            "examples": [],
            "dimensionTags": {
                "framework": "tum-ph0008",
                "demandLevel": "AB2",
                "processCompetencies": [],
                "guidingIdeas": [],
                "phase": "Modul",
                "area": "Gesamtkompetenz",
                "topicCode": "tum_ph0008_module"
            }
        },
        {
            "id": "0ad131b5-1205-4e6b-9795-270510338340",
            "shortKey": "tum_ph0008_lo1",
            "title": "Statistische Begründung der Thermodynamik",
            "titleEn": "Statistical Justification of Thermodynamics",
            "description": "Die lernende Person kann mikrokanonische, kanonische und großkanonische Gesamtheiten formulieren, Entropie/Zustandssumme nutzen und Hauptsätze der Thermodynamik statistisch begründen.",
            "descriptionEn": "The learner can formulate microcanonical, canonical, and grand canonical ensembles, use entropy/partition function, and statistically justify the laws of thermodynamics.",
            "core": true,
            "weight": 1.4,
            "phase": "Modul",
            "area": "Statistische Grundlagen",
            "tags": [
                "ects:9",
                "module:PH0008"
            ],
            "contains": [
                "b4966e6d-ca32-4dd1-96e0-044bbde9d911",
                "ef598102-d2c4-4bb3-a9a6-e11f3862ea2a",
                "e9bde401-6504-4284-860c-4b3ab83b56ec",
                "4e44f4e6-b8c0-4483-aeea-13749d09f3c5",
                "c303d2ab-5ae3-4043-95d4-9272e35e4d2a"
            ],
            "requires": [],
            "examples": [],
            "dimensionTags": {
                "framework": "tum-ph0008",
                "demandLevel": "AB2",
                "processCompetencies": [],
                "guidingIdeas": [],
                "phase": "Modul",
                "area": "Statistische Grundlagen",
                "topicCode": "tum_ph0008_lo1"
            }
        },
        {
            "id": "b4966e6d-ca32-4dd1-96e0-044bbde9d911",
            "shortKey": "tum_ph0008_lo1_1",
            "title": "Mikrokanonische Gesamtheit und Entropie",
            "titleEn": "Microcanonical Ensemble and Entropy",
            "description": "Die lernende Person kann mikrokanonische Gesamtheiten, Gleichwahrscheinlichkeitsannahme, Zustandssumme und Entropie definieren.",
            "descriptionEn": "The learner can define microcanonical ensembles, the equal probability assumption, partition function, and entropy.",
            "core": true,
            "weight": 0.28,
            "phase": "Modul",
            "area": "Statistische Grundlagen",
            "tags": [
                "ects:9",
                "module:PH0008"
            ],
            "requires": [],
            "contains": [],
            "examples": [],
            "dimensionTags": {
                "framework": "tum-ph0008",
                "demandLevel": "AB2",
                "processCompetencies": [],
                "guidingIdeas": [],
                "phase": "Modul",
                "area": "Statistische Grundlagen",
                "topicCode": "tum_ph0008_lo1_1"
            }
        },
        {
            "id": "ef598102-d2c4-4bb3-a9a6-e11f3862ea2a",
            "shortKey": "tum_ph0008_lo1_2",
            "title": "Kanonische und großkanonische Ensembles",
            "titleEn": "Canonical and Grand Canonical Ensembles",
            "description": "Die lernende Person kann kanonische und großkanonische Gesamtheiten aufstellen und thermodynamische Größen daraus ableiten.",
            "descriptionEn": "The learner can set up canonical and grand canonical ensembles and derive thermodynamic quantities from them.",
            "core": true,
            "weight": 0.28,
            "phase": "Modul",
            "area": "Statistische Grundlagen",
            "tags": [
                "ects:9",
                "module:PH0008"
            ],
            "requires": [
                "b4966e6d-ca32-4dd1-96e0-044bbde9d911"
            ],
            "contains": [],
            "examples": [],
            "dimensionTags": {
                "framework": "tum-ph0008",
                "demandLevel": "AB2",
                "processCompetencies": [],
                "guidingIdeas": [],
                "phase": "Modul",
                "area": "Statistische Grundlagen",
                "topicCode": "tum_ph0008_lo1_2"
            }
        },
        {
            "id": "e9bde401-6504-4284-860c-4b3ab83b56ec",
            "shortKey": "tum_ph0008_lo1_3",
            "title": "Maxwell-Boltzmann-Verteilung und Gleichverteilungssatz",
            "titleEn": "Maxwell-Boltzmann Distribution and Equipartition Theorem",
            "description": "Die lernende Person kann die MB-Verteilung herleiten und den Gleichverteilungssatz anwenden.",
            "descriptionEn": "The learner can derive the MB distribution and apply the equipartition theorem.",
            "core": true,
            "weight": 0.28,
            "phase": "Modul",
            "area": "Statistische Grundlagen",
            "tags": [
                "ects:9",
                "module:PH0008"
            ],
            "requires": [
                "ef598102-d2c4-4bb3-a9a6-e11f3862ea2a"
            ],
            "contains": [],
            "examples": [],
            "dimensionTags": {
                "framework": "tum-ph0008",
                "demandLevel": "AB2",
                "processCompetencies": [],
                "guidingIdeas": [],
                "phase": "Modul",
                "area": "Statistische Grundlagen",
                "topicCode": "tum_ph0008_lo1_3"
            }
        },
        {
            "id": "4e44f4e6-b8c0-4483-aeea-13749d09f3c5",
            "shortKey": "tum_ph0008_lo1_4",
            "title": "Hauptsätze, reversible/irreversible Prozesse",
            "titleEn": "Laws of Thermodynamics, Reversible/Irreversible Processes",
            "description": "Die lernende Person kann Hauptsätze der Thermodynamik statistisch begründen und reversible/irreversible Prozesse diskutieren.",
            "descriptionEn": "The learner can statistically justify the laws of thermodynamics and discuss reversible/irreversible processes.",
            "core": true,
            "weight": 0.28,
            "phase": "Modul",
            "area": "Statistische Grundlagen",
            "tags": [
                "ects:9",
                "module:PH0008"
            ],
            "requires": [
                "ef598102-d2c4-4bb3-a9a6-e11f3862ea2a"
            ],
            "contains": [],
            "examples": [],
            "dimensionTags": {
                "framework": "tum-ph0008",
                "demandLevel": "AB2",
                "processCompetencies": [],
                "guidingIdeas": [],
                "phase": "Modul",
                "area": "Statistische Grundlagen",
                "topicCode": "tum_ph0008_lo1_4"
            }
        },
        {
            "id": "c303d2ab-5ae3-4043-95d4-9272e35e4d2a",
            "shortKey": "tum_ph0008_lo1_5",
            "title": "Wärme, Arbeit, Temperatur",
            "titleEn": "Heat, Work, Temperature",
            "description": "Die lernende Person kann Wärme, Arbeit und Temperatur in statistischer Mechanik definieren und ihre Zusammenhänge nutzen.",
            "descriptionEn": "The learner can define heat, work, and temperature in statistical mechanics and use their relationships.",
            "core": true,
            "weight": 0.28,
            "phase": "Modul",
            "area": "Statistische Grundlagen",
            "tags": [
                "ects:9",
                "module:PH0008"
            ],
            "requires": [
                "ef598102-d2c4-4bb3-a9a6-e11f3862ea2a"
            ],
            "contains": [],
            "examples": [],
            "dimensionTags": {
                "framework": "tum-ph0008",
                "demandLevel": "AB2",
                "processCompetencies": [],
                "guidingIdeas": [],
                "phase": "Modul",
                "area": "Statistische Grundlagen",
                "topicCode": "tum_ph0008_lo1_5"
            }
        },
        {
            "id": "7d7a839e-064d-40cf-8c9d-7a668be9f0e8",
            "shortKey": "tum_ph0008_lo2",
            "title": "Phänomenologische Thermodynamik",
            "titleEn": "Phenomenological Thermodynamics",
            "description": "Die lernende Person kann thermodynamische Potentiale, Maxwell-Relationen, Kreisprozesse, Stabilität sowie Phasenübergänge und mehrkomponentige Systeme beschreiben.",
            "descriptionEn": "The learner can describe thermodynamic potentials, Maxwell relations, cycles, stability, as well as phase transitions and multi-component systems.",
            "core": true,
            "weight": 1.4,
            "phase": "Modul",
            "area": "Thermodynamik",
            "tags": [
                "ects:9",
                "module:PH0008"
            ],
            "contains": [
                "3665a206-aee6-45c9-a56d-0c55e061725a",
                "f6f9fb8d-5c70-4d08-be61-c2562a305838",
                "a4ca5645-7ab0-47e2-84a2-fac731028ce6",
                "33fb2223-3446-4b05-997f-4d6f31e7c19c",
                "bbd57688-8a29-4c86-9b06-5890030b03f4"
            ],
            "requires": [
                "0ad131b5-1205-4e6b-9795-270510338340"
            ],
            "examples": [],
            "dimensionTags": {
                "framework": "tum-ph0008",
                "demandLevel": "AB2",
                "processCompetencies": [],
                "guidingIdeas": [],
                "phase": "Modul",
                "area": "Thermodynamik",
                "topicCode": "tum_ph0008_lo2"
            }
        },
        {
            "id": "3665a206-aee6-45c9-a56d-0c55e061725a",
            "shortKey": "tum_ph0008_lo2_1",
            "title": "Thermodynamische Potentiale und Stabilität",
            "titleEn": "Thermodynamic Potentials and Stability",
            "description": "Die lernende Person kann thermodynamische Potentiale und Stabilitätskriterien anwenden, Maxwell-Relationen nutzen.",
            "descriptionEn": "The learner can apply thermodynamic potentials and stability criteria, and use Maxwell relations.",
            "core": true,
            "weight": 0.28,
            "phase": "Modul",
            "area": "Thermodynamik",
            "tags": [
                "ects:9",
                "module:PH0008"
            ],
            "requires": [],
            "contains": [],
            "examples": [],
            "dimensionTags": {
                "framework": "tum-ph0008",
                "demandLevel": "AB2",
                "processCompetencies": [],
                "guidingIdeas": [],
                "phase": "Modul",
                "area": "Thermodynamik",
                "topicCode": "tum_ph0008_lo2_1"
            }
        },
        {
            "id": "f6f9fb8d-5c70-4d08-be61-c2562a305838",
            "shortKey": "tum_ph0008_lo2_2",
            "title": "Kreisprozesse und Wärmekraftmaschinen",
            "titleEn": "Cycles and Heat Engines",
            "description": "Die lernende Person kann Kreisprozesse und Wärmekraftmaschinen beschreiben und Wirkungsgrade diskutieren.",
            "descriptionEn": "The learner can describe cycles and heat engines and discuss efficiencies.",
            "core": true,
            "weight": 0.28,
            "phase": "Modul",
            "area": "Thermodynamik",
            "tags": [
                "ects:9",
                "module:PH0008"
            ],
            "requires": [
                "3665a206-aee6-45c9-a56d-0c55e061725a"
            ],
            "contains": [],
            "examples": [],
            "dimensionTags": {
                "framework": "tum-ph0008",
                "demandLevel": "AB2",
                "processCompetencies": [],
                "guidingIdeas": [],
                "phase": "Modul",
                "area": "Thermodynamik",
                "topicCode": "tum_ph0008_lo2_2"
            }
        },
        {
            "id": "a4ca5645-7ab0-47e2-84a2-fac731028ce6",
            "shortKey": "tum_ph0008_lo2_3",
            "title": "Phasen und Phasenübergänge",
            "titleEn": "Phases and Phase Transitions",
            "description": "Die lernende Person kann Phasenübergänge, Clausius-Clapeyron-Gleichung und van-der-Waals-Gleichung beschreiben.",
            "descriptionEn": "The learner can describe phase transitions, Clausius-Clapeyron equation, and van der Waals equation.",
            "core": true,
            "weight": 0.28,
            "phase": "Modul",
            "area": "Thermodynamik",
            "tags": [
                "ects:9",
                "module:PH0008"
            ],
            "requires": [
                "3665a206-aee6-45c9-a56d-0c55e061725a"
            ],
            "contains": [],
            "examples": [],
            "dimensionTags": {
                "framework": "tum-ph0008",
                "demandLevel": "AB2",
                "processCompetencies": [],
                "guidingIdeas": [],
                "phase": "Modul",
                "area": "Thermodynamik",
                "topicCode": "tum_ph0008_lo2_3"
            }
        },
        {
            "id": "33fb2223-3446-4b05-997f-4d6f31e7c19c",
            "shortKey": "tum_ph0008_lo2_4",
            "title": "Mehrkomponentige Systeme und Osmose",
            "titleEn": "Multi-Component Systems and Osmosis",
            "description": "Die lernende Person kann Mehrkomponentensysteme und Osmose einordnen.",
            "descriptionEn": "The learner can classify multi-component systems and osmosis.",
            "core": true,
            "weight": 0.28,
            "phase": "Modul",
            "area": "Thermodynamik",
            "tags": [
                "ects:9",
                "module:PH0008"
            ],
            "requires": [
                "a4ca5645-7ab0-47e2-84a2-fac731028ce6"
            ],
            "contains": [],
            "examples": [],
            "dimensionTags": {
                "framework": "tum-ph0008",
                "demandLevel": "AB2",
                "processCompetencies": [],
                "guidingIdeas": [],
                "phase": "Modul",
                "area": "Thermodynamik",
                "topicCode": "tum_ph0008_lo2_4"
            }
        },
        {
            "id": "bbd57688-8a29-4c86-9b06-5890030b03f4",
            "shortKey": "tum_ph0008_lo2_5",
            "title": "Kühlung, Expansion und Zustandsänderungen",
            "titleEn": "Cooling, Expansion, and Changes of State",
            "description": "Die lernende Person kann Kühlung durch Expansion, Zustandsänderungen und thermodynamische Stabilitätsaspekte beschreiben.",
            "descriptionEn": "The learner can describe cooling by expansion, changes of state, and thermodynamic stability aspects.",
            "core": true,
            "weight": 0.28,
            "phase": "Modul",
            "area": "Thermodynamik",
            "tags": [
                "ects:9",
                "module:PH0008"
            ],
            "requires": [
                "f6f9fb8d-5c70-4d08-be61-c2562a305838"
            ],
            "contains": [],
            "examples": [],
            "dimensionTags": {
                "framework": "tum-ph0008",
                "demandLevel": "AB2",
                "processCompetencies": [],
                "guidingIdeas": [],
                "phase": "Modul",
                "area": "Thermodynamik",
                "topicCode": "tum_ph0008_lo2_5"
            }
        },
        {
            "id": "3ced904f-a2b5-4e56-b5d7-526a81b46460",
            "shortKey": "tum_ph0008_lo3",
            "title": "Statistische Physik spezieller Systeme",
            "titleEn": "Statistical Physics of Special Systems",
            "description": "Die lernende Person kann Quantengase (Fermi/Bose), Strahlung/Photonen/Phononen, Magnetismus (z. B. Ising), Virialentwicklung und van-der-Waals-Modelle einordnen; BE-Kondensation beschreiben.",
            "descriptionEn": "The learner can classify quantum gases (Fermi/Bose), radiation/photons/phonons, magnetism (e.g. Ising), virial expansion and van der Waals models; describe BE condensation.",
            "core": true,
            "weight": 1.4,
            "phase": "Modul",
            "area": "Statistische Physik",
            "tags": [
                "ects:9",
                "module:PH0008"
            ],
            "contains": [
                "bbb5115a-2215-4700-afe0-fff99aec4962",
                "d52090a2-bef8-4a5d-aee6-53ce282eebd8",
                "2c67a8a4-7079-455b-b158-82e7a07b294d",
                "0154a575-46ca-4f5f-993a-a643623266e8"
            ],
            "requires": [
                "0ad131b5-1205-4e6b-9795-270510338340"
            ],
            "examples": [],
            "dimensionTags": {
                "framework": "tum-ph0008",
                "demandLevel": "AB2",
                "processCompetencies": [],
                "guidingIdeas": [],
                "phase": "Modul",
                "area": "Statistische Physik",
                "topicCode": "tum_ph0008_lo3"
            }
        },
        {
            "id": "bbb5115a-2215-4700-afe0-fff99aec4962",
            "shortKey": "tum_ph0008_lo3_1",
            "title": "Wechselwirkungsfreie Quantengase",
            "titleEn": "Interaction-Free Quantum Gases",
            "description": "Die lernende Person kann ideales Fermigas und ideales Bose-Gas (inkl. Entartung und BE-Kondensation) beschreiben und klassischen Limes herstellen.",
            "descriptionEn": "The learner can describe ideal Fermi gas and ideal Bose gas (incl. degeneracy and BE condensation) and establish the classical limit.",
            "core": true,
            "weight": 0.35,
            "phase": "Modul",
            "area": "Statistische Physik",
            "tags": [
                "ects:9",
                "module:PH0008"
            ],
            "requires": [
                "ef598102-d2c4-4bb3-a9a6-e11f3862ea2a"
            ],
            "contains": [],
            "examples": [],
            "dimensionTags": {
                "framework": "tum-ph0008",
                "demandLevel": "AB2",
                "processCompetencies": [],
                "guidingIdeas": [],
                "phase": "Modul",
                "area": "Statistische Physik",
                "topicCode": "tum_ph0008_lo3_1"
            }
        },
        {
            "id": "d52090a2-bef8-4a5d-aee6-53ce282eebd8",
            "shortKey": "tum_ph0008_lo3_2",
            "title": "Strahlung, Photonen und Phononen",
            "titleEn": "Radiation, Photons, and Phonons",
            "description": "Die lernende Person kann Thermodynamik der Strahlung sowie Photonen- und Phononengase beschreiben.",
            "descriptionEn": "The learner can describe the thermodynamics of radiation as well as photon and phonon gases.",
            "core": true,
            "weight": 0.35,
            "phase": "Modul",
            "area": "Statistische Physik",
            "tags": [
                "ects:9",
                "module:PH0008"
            ],
            "requires": [
                "e9bde401-6504-4284-860c-4b3ab83b56ec"
            ],
            "contains": [],
            "examples": [],
            "dimensionTags": {
                "framework": "tum-ph0008",
                "demandLevel": "AB2",
                "processCompetencies": [],
                "guidingIdeas": [],
                "phase": "Modul",
                "area": "Statistische Physik",
                "topicCode": "tum_ph0008_lo3_2"
            }
        },
        {
            "id": "2c67a8a4-7079-455b-b158-82e7a07b294d",
            "shortKey": "tum_ph0008_lo3_3",
            "title": "Magnetische Phänomene und Ising-Modell",
            "titleEn": "Magnetic Phenomena and Ising Model",
            "description": "Die lernende Person kann einfache magnetische Modelle und das Ising-Modell qualitativ einordnen.",
            "descriptionEn": "The learner can qualitatively classify simple magnetic models and the Ising model.",
            "core": true,
            "weight": 0.3,
            "phase": "Modul",
            "area": "Statistische Physik",
            "tags": [
                "ects:9",
                "module:PH0008"
            ],
            "requires": [
                "e9bde401-6504-4284-860c-4b3ab83b56ec"
            ],
            "contains": [],
            "examples": [],
            "dimensionTags": {
                "framework": "tum-ph0008",
                "demandLevel": "AB2",
                "processCompetencies": [],
                "guidingIdeas": [],
                "phase": "Modul",
                "area": "Statistische Physik",
                "topicCode": "tum_ph0008_lo3_3"
            }
        },
        {
            "id": "0154a575-46ca-4f5f-993a-a643623266e8",
            "shortKey": "tum_ph0008_lo3_4",
            "title": "Wechselwirkungen: Virialentwicklung und van der Waals",
            "titleEn": "Interactions: Virial Expansion and Van der Waals",
            "description": "Die lernende Person kann Virialentwicklung und van-der-Waals-Gleichung als Modelle wechselwirkender Gase diskutieren.",
            "descriptionEn": "The learner can discuss virial expansion and van der Waals equation as models of interacting gases.",
            "core": true,
            "weight": 0.4,
            "phase": "Modul",
            "area": "Statistische Physik",
            "tags": [
                "ects:9",
                "module:PH0008"
            ],
            "requires": [
                "bbb5115a-2215-4700-afe0-fff99aec4962",
                "a4ca5645-7ab0-47e2-84a2-fac731028ce6"
            ],
            "contains": [],
            "examples": [],
            "dimensionTags": {
                "framework": "tum-ph0008",
                "demandLevel": "AB2",
                "processCompetencies": [],
                "guidingIdeas": [],
                "phase": "Modul",
                "area": "Statistische Physik",
                "topicCode": "tum_ph0008_lo3_4"
            }
        },
        {
            "id": "256e621c-c8ec-4a6b-ab01-cd3fcc34605e",
            "shortKey": "tum_ph0008_lo4",
            "title": "Nichtgleichgewichts-Thermodynamik",
            "titleEn": "Non-Equilibrium Thermodynamics",
            "description": "Die lernende Person kann Grundbegriffe der kinetischen Theorie, Boltzmann-Gleichung, Diffusion, Brownsche Bewegung und Fluktuations-Dissipations-Theorem anwenden.",
            "descriptionEn": "The learner can apply basic concepts of kinetic theory, Boltzmann equation, diffusion, Brownian motion, and fluctuation-dissipation theorem.",
            "core": true,
            "weight": 1.2,
            "phase": "Modul",
            "area": "Nichtgleichgewicht",
            "tags": [
                "ects:9",
                "module:PH0008"
            ],
            "contains": [
                "6e4a0351-e768-475b-b1a8-7753c9b10166",
                "29976bfa-0e15-4aa5-b75e-3612b459e450",
                "fe140ca8-8593-4001-b9d2-53398dd42b7a"
            ],
            "requires": [
                "0ad131b5-1205-4e6b-9795-270510338340"
            ],
            "examples": [],
            "dimensionTags": {
                "framework": "tum-ph0008",
                "demandLevel": "AB2",
                "processCompetencies": [],
                "guidingIdeas": [],
                "phase": "Modul",
                "area": "Nichtgleichgewicht",
                "topicCode": "tum_ph0008_lo4"
            }
        },
        {
            "id": "6e4a0351-e768-475b-b1a8-7753c9b10166",
            "shortKey": "tum_ph0008_lo4_1",
            "title": "Boltzmann-Gleichung und kinetische Theorie",
            "titleEn": "Boltzmann Equation and Kinetic Theory",
            "description": "Die lernende Person kann Grundideen der Boltzmann-Gleichung und der kinetischen Theorie anwenden.",
            "descriptionEn": "The learner can apply basic ideas of the Boltzmann equation and kinetic theory.",
            "core": true,
            "weight": 0.4,
            "phase": "Modul",
            "area": "Nichtgleichgewicht",
            "tags": [
                "ects:9",
                "module:PH0008"
            ],
            "requires": [
                "ef598102-d2c4-4bb3-a9a6-e11f3862ea2a"
            ],
            "contains": [],
            "examples": [],
            "dimensionTags": {
                "framework": "tum-ph0008",
                "demandLevel": "AB2",
                "processCompetencies": [],
                "guidingIdeas": [],
                "phase": "Modul",
                "area": "Nichtgleichgewicht",
                "topicCode": "tum_ph0008_lo4_1"
            }
        },
        {
            "id": "29976bfa-0e15-4aa5-b75e-3612b459e450",
            "shortKey": "tum_ph0008_lo4_2",
            "title": "Diffusion und Einstein-Relation",
            "titleEn": "Diffusion and Einstein Relation",
            "description": "Die lernende Person kann Teilchen- und Wärmediffusion beschreiben und die Einstein-Relation anwenden.",
            "descriptionEn": "The learner can describe particle and heat diffusion and apply the Einstein relation.",
            "core": true,
            "weight": 0.4,
            "phase": "Modul",
            "area": "Nichtgleichgewicht",
            "tags": [
                "ects:9",
                "module:PH0008"
            ],
            "requires": [
                "6e4a0351-e768-475b-b1a8-7753c9b10166"
            ],
            "contains": [],
            "examples": [],
            "dimensionTags": {
                "framework": "tum-ph0008",
                "demandLevel": "AB2",
                "processCompetencies": [],
                "guidingIdeas": [],
                "phase": "Modul",
                "area": "Nichtgleichgewicht",
                "topicCode": "tum_ph0008_lo4_2"
            }
        },
        {
            "id": "fe140ca8-8593-4001-b9d2-53398dd42b7a",
            "shortKey": "tum_ph0008_lo4_3",
            "title": "Brownsche Bewegung und Fluktuations-Dissipation",
            "titleEn": "Brownian Motion and Fluctuation-Dissipation",
            "description": "Die lernende Person kann Brownsche Bewegung und das Fluktuations-Dissipations-Theorem qualitativ und quantitativ einordnen.",
            "descriptionEn": "The learner can qualitatively and quantitatively classify Brownian motion and the fluctuation-dissipation theorem.",
            "core": true,
            "weight": 0.4,
            "phase": "Modul",
            "area": "Nichtgleichgewicht",
            "tags": [
                "ects:9",
                "module:PH0008"
            ],
            "requires": [
                "6e4a0351-e768-475b-b1a8-7753c9b10166"
            ],
            "contains": [],
            "examples": [],
            "dimensionTags": {
                "framework": "tum-ph0008",
                "demandLevel": "AB2",
                "processCompetencies": [],
                "guidingIdeas": [],
                "phase": "Modul",
                "area": "Nichtgleichgewicht",
                "topicCode": "tum_ph0008_lo4_3"
            }
        }
    ]
}